compression_distance/__init__.py
compression_distance/compression_distance.py
compression_distance-0.1.1.dist-info/METADATA
compression_distance-0.1.1.dist-info/WHEEL
compression_distance-0.1.1.dist-info/top_level.txt
compression_distance-0.1.1.dist-info/RECORD
