Metadata-Version: 2.2
Name: compression-distance
Version: 0.1.1
Summary: A compression-based edit distance metric for text comparison
Home-page: https://github.com/NDV-tiime/CompressionDistance
Author: Nicolas Devatine & Louis Abraham
Author-email: nicolas.devatine@tiime.fr
Requires-Python: >=3.9
Requires-Dist: numpy
Requires-Dist: pandas
Requires-Dist: scikit-learn
Requires-Dist: scipy
Requires-Dist: tqdm
Requires-Dist: evaluate
Requires-Dist: nltk
Requires-Dist: unidecode
Requires-Dist: pydivsufsort
Requires-Dist: Levenshtein
Requires-Dist: pytest
Provides-Extra: experiments
Requires-Dist: evaluate; extra == "experiments"
Requires-Dist: datasets; extra == "experiments"
Requires-Dist: bert_score; extra == "experiments"
Requires-Dist: sacrebleu; extra == "experiments"
Requires-Dist: rouge_score; extra == "experiments"
Requires-Dist: cer; extra == "experiments"
Dynamic: author
Dynamic: author-email
Dynamic: description
Dynamic: description-content-type
Dynamic: home-page
Dynamic: provides-extra
Dynamic: requires-dist
Dynamic: requires-python
Dynamic: summary
